hbutils/__init__.py
hbutils/algorithm/__init__.py
hbutils/algorithm/linear.py
hbutils/algorithm/topological.py
hbutils/binary/__init__.py
hbutils/binary/base.py
hbutils/binary/bool.py
hbutils/binary/buffer.py
hbutils/binary/float.py
hbutils/binary/int.py
hbutils/binary/str.py
hbutils/binary/uint.py
hbutils/collection/__init__.py
hbutils/collection/dimension.py
hbutils/collection/functional.py
hbutils/collection/recover.py
hbutils/collection/sequence.py
hbutils/collection/stacked.py
hbutils/collection/structural.py
hbutils/color/__init__.py
hbutils/color/base.py
hbutils/color/model.py
hbutils/color/utils.py
hbutils/concurrent/__init__.py
hbutils/concurrent/parallel.py
hbutils/concurrent/readwrite.py
hbutils/config/__init__.py
hbutils/config/meta.py
hbutils/design/__init__.py
hbutils/design/decorator.py
hbutils/design/final.py
hbutils/design/observer.py
hbutils/design/singleton.py
hbutils/encoding/__init__.py
hbutils/encoding/ansi.py
hbutils/encoding/base64.py
hbutils/encoding/decode.py
hbutils/encoding/hash.py
hbutils/encoding/int_hash.py
hbutils/encoding/int_hash_val.py
hbutils/expression/__init__.py
hbutils/expression/native/__init__.py
hbutils/expression/native/base.py
hbutils/expression/native/feature.py
hbutils/expression/native/general.py
hbutils/file/__init__.py
hbutils/file/stream.py
hbutils/logging/__init__.py
hbutils/logging/format.py
hbutils/logging/progress.py
hbutils/model/__init__.py
hbutils/model/_info.py
hbutils/model/clazz.py
hbutils/model/compare.py
hbutils/model/enum.py
hbutils/model/raw.py
hbutils/model/repr.py
hbutils/random/__init__.py
hbutils/random/binary.py
hbutils/random/sequence.py
hbutils/random/state.py
hbutils/random/string.py
hbutils/reflection/__init__.py
hbutils/reflection/clazz.py
hbutils/reflection/context.py
hbutils/reflection/exception.py
hbutils/reflection/func.py
hbutils/reflection/imports.py
hbutils/reflection/iter.py
hbutils/reflection/module.py
hbutils/scale/__init__.py
hbutils/scale/size.py
hbutils/scale/time.py
hbutils-0.14.2.dist-info/LICENSE
hbutils-0.14.2.dist-info/METADATA
hbutils-0.14.2.dist-info/WHEEL
hbutils-0.14.2.dist-info/top_level.txt
hbutils-0.14.2.dist-info/RECORD
