Metadata-Version: 2.1
Name: hbutils
Version: 0.14.2
Summary: Some useful functions and classes in Python infrastructure development.
Home-page: https://github.com/HansBug/hbutils
Author: HansBug
Author-email: hansbug@buaa.edu.cn
License: Apache License, Version 2.0
Project-URL: Homepage, https://github.com/HansBug/hbutils
Project-URL: Documentation, https://hbutils.readthedocs.io/en/latest/
Project-URL: Repository, https://github.com/HansBug/hbutils
Project-URL: Bug Reports, https://github.com/HansBug/hbutils/issues
Project-URL: Source, https://github.com/HansBug/hbutils
Keywords: python,generic,utilities,algorithms,data structures,system operations,design patterns,testing tools
Classifier: Development Status :: 5 - Production/Stable
Classifier: Intended Audience :: Developers
Classifier: Intended Audience :: Information Technology
Classifier: Intended Audience :: Science/Research
Classifier: Intended Audience :: System Administrators
Classifier: License :: OSI Approved :: Apache Software License
Classifier: Operating System :: OS Independent
Classifier: Operating System :: POSIX
Classifier: Operating System :: POSIX :: Linux
Classifier: Operating System :: Microsoft :: Windows
Classifier: Operating System :: MacOS
Classifier: Programming Language :: Python
Classifier: Programming Language :: Python :: 3
Classifier: Programming Language :: Python :: 3 :: Only
Classifier: Programming Language :: Python :: 3.7
Classifier: Programming Language :: Python :: 3.8
Classifier: Programming Language :: Python :: 3.9
Classifier: Programming Language :: Python :: 3.10
Classifier: Programming Language :: Python :: 3.11
Classifier: Programming Language :: Python :: 3.12
Classifier: Programming Language :: Python :: 3.13
Classifier: Programming Language :: Python :: Implementation :: CPython
Classifier: Programming Language :: Python :: Implementation :: PyPy
Classifier: Topic :: Software Development
Classifier: Topic :: Software Development :: Libraries
Classifier: Topic :: Software Development :: Libraries :: Python Modules
Classifier: Topic :: Utilities
Classifier: Topic :: System :: Systems Administration
Classifier: Topic :: Scientific/Engineering
Classifier: Topic :: Text Processing
Classifier: Topic :: Software Development :: Testing
Classifier: Natural Language :: English
Classifier: Environment :: Console
Classifier: Environment :: Other Environment
Classifier: Framework :: Pytest
Classifier: Typing :: Typed
Requires-Python: >=3.7
License-File: LICENSE
Requires-Dist: packaging >=21.3
Requires-Dist: setuptools >=50.0
Requires-Dist: pytimeparse >=1.1.8
Requires-Dist: bitmath >=1.3.3.1
Requires-Dist: chardet <5,>=3.0.4
Requires-Dist: deprecation >=2.0.0
Requires-Dist: importlib-metadata >=6.0.0 ; python_version < "3.8"
Requires-Dist: typing-extensions >=3.7.4 ; python_version < "3.8"
Provides-Extra: dev
Requires-Dist: openai ; extra == 'dev'
Requires-Dist: ruff ; extra == 'dev'
Provides-Extra: doc
Requires-Dist: Jinja2 >=3.0.0 ; extra == 'doc'
Requires-Dist: sphinx >=3.2.0 ; extra == 'doc'
Requires-Dist: sphinx-rtd-theme >=0.4.3 ; extra == 'doc'
Requires-Dist: enum-tools >=0.9.0 ; extra == 'doc'
Requires-Dist: sphinx-toolbox ; extra == 'doc'
Requires-Dist: plantumlcli >=0.0.2 ; extra == 'doc'
Requires-Dist: packaging ; extra == 'doc'
Requires-Dist: sphinx-multiversion >=0.2.4 ; extra == 'doc'
Requires-Dist: where >=1.0.2 ; extra == 'doc'
Requires-Dist: easydict <2,>=1.7 ; extra == 'doc'
Requires-Dist: natsort ; extra == 'doc'
Provides-Extra: test
Requires-Dist: coverage >=5 ; extra == 'test'
Requires-Dist: mock >=4.0.3 ; extra == 'test'
Requires-Dist: flake8 ~=3.5 ; extra == 'test'
Requires-Dist: pytest ~=6.2.5 ; extra == 'test'
Requires-Dist: pytest-cov ~=3.0.0 ; extra == 'test'
Requires-Dist: pytest-mock ~=3.6.1 ; extra == 'test'
Requires-Dist: pytest-xdist >=1.34.0 ; extra == 'test'
Requires-Dist: pytest-rerunfailures ~=10.2 ; extra == 'test'
Requires-Dist: pytest-timeout ~=2.0.2 ; extra == 'test'
Requires-Dist: easydict <2,>=1.7 ; extra == 'test'
Requires-Dist: click >=7.0.0 ; extra == 'test'
Requires-Dist: requests[socks] >=2.20 ; extra == 'test'
Requires-Dist: testtools >=2 ; extra == 'test'
Requires-Dist: tqdm ; extra == 'test'
Requires-Dist: numpy >=1.20 ; (implementation_name != "pypy" or platform_system != "Windows" or python_version >= "3.8") and extra == 'test'
Requires-Dist: torch >=1.1.0 ; (python_version < "3.11" and implementation_name != "pypy") and extra == 'test'
Requires-Dist: faker ; (python_version > "3.7") and extra == 'test'
